MANIFEST.in
README.md
setup.py
backoffice/__init__.py
backoffice/client.py
backoffice/conftest.py
backoffice/http.py
backoffice/orders.py
backoffice/processors.py
backoffice/schemas/items.schema.json
backoffice/schemas/order.schema.json
backoffice/tests/__init__.py
backoffice/tests/test_get.py
backoffice/tests/test_get_offers.py
backoffice/tests/test_http.py
backoffice/tests/test_http_append_qs.py
backoffice/tests/test_http_pagination.py
backoffice/tests/test_items_fetching.py
backoffice/tests/test_processors.py
backoffice/tests/test_product_offer_count.py
backoffice/tests/test_product_orders_stat.py
backoffice/tests/test_product_sales_stat.py
backoffice/tests/test_submitting_lead.py
backoffice/tests/test_submitting_order.py
backoffice/tests/test_validation.py
gm_backoffice_client.egg-info/PKG-INFO
gm_backoffice_client.egg-info/SOURCES.txt
gm_backoffice_client.egg-info/dependency_links.txt
gm_backoffice_client.egg-info/not-zip-safe
gm_backoffice_client.egg-info/requires.txt
gm_backoffice_client.egg-info/top_level.txt