Metadata-Version: 1.0
Name: gm-backoffice-client
Version: 1.3.0
Summary: Client for mtrl.ai orders API
Home-page: https://github.com/gdml/backoffice-client/
Author: Fedor Borshev
Author-email: f@f213.in
License: MIT
Platform: UNKNOWN
